[
  {
    "district_name": "Ambawadi"
  },
  {
    "district_name": "Ambli"
  },
  {
    "district_name": "Amraiwadi"
  },
  {
    "district_name": "Anandnagar"
  },
  {
    "district_name": "Asarwa"
  },
  {
    "district_name": "Ashram"
  },
  {
    "district_name": "Aslali"
  },
  {
    "district_name": "Azad"
  },
  {
    "district_name": "Bakrol"
  },
  {
    "district_name": "Bapunagar"
  },
  {
    "district_name": "Bareja"
  },
  {
    "district_name": "Behrampura"
  },
  {
    "district_name": "Bhairavnath"
  },
  {
    "district_name": "Bhat"
  },
  {
    "district_name": "Bhavda"
  },
  {
    "district_name": "Bhuvaldi"
  },
  {
    "district_name": "Bilasia"
  },
  {
    "district_name": "Bodakdev"
  },
  {
    "district_name": "Bopal"
  },
  {
    "district_name": "Calico"
  },
  {
    "district_name": "Cantonment"
  },
  {
    "district_name": "Chandial"
  },
  {
    "district_name": "Chandkheda"
  },
  {
    "district_name": "Chaulaj"
  },
  {
    "district_name": "Civil"
  },
  {
    "district_name": "Ctm"
  },
  {
    "district_name": "D"
  },
  {
    "district_name": "Dariapur"
  },
  {
    "district_name": "Darpan"
  },
  {
    "district_name": "Daxini"
  },
  {
    "district_name": "Delhi"
  },
  {
    "district_name": "Dhamatvan"
  },
  {
    "district_name": "District"
  },
  {
    "district_name": "Dudheshwar"
  },
  {
    "district_name": "Ellisbridge"
  },
  {
    "district_name": "Fatewadi"
  },
  {
    "district_name": "Gamdi"
  },
  {
    "district_name": "Gandhi"
  },
  {
    "district_name": "Geratpur"
  },
  {
    "district_name": "Ghatlodia"
  },
  {
    "district_name": "Gheekanta"
  },
  {
    "district_name": "Ghodasar"
  },
  {
    "district_name": "Ghuma"
  },
  {
    "district_name": "Girdharnagar"
  },
  {
    "district_name": "Girmatha"
  },
  {
    "district_name": "Gita"
  },
  {
    "district_name": "Gomtipur"
  },
  {
    "district_name": "Gujarat"
  },
  {
    "district_name": "Gyaspur"
  },
  {
    "district_name": "Harniav"
  },
  {
    "district_name": "Hirapur"
  },
  {
    "district_name": "I"
  },
  {
    "district_name": "Isanpur"
  },
  {
    "district_name": "Jamalpur"
  },
  {
    "district_name": "Jawahar"
  },
  {
    "district_name": "Jetalpur"
  },
  {
    "district_name": "Jivraj"
  },
  {
    "district_name": "Jodhpur"
  },
  {
    "district_name": "Juhapura"
  },
  {
    "district_name": "Kabir"
  },
  {
    "district_name": "Kalupur"
  },
  {
    "district_name": "Kanbha"
  },
  {
    "district_name": "Kaniyel"
  },
  {
    "district_name": "Kasindra"
  },
  {
    "district_name": "Kathwada"
  },
  {
    "district_name": "Kathwada Maize Product"
  },
  {
    "district_name": "Khadia"
  },
  {
    "district_name": "Khanpur Ahmedabad"
  },
  {
    "district_name": "Khodiyarnagar"
  },
  {
    "district_name": "Khokhara Mehmadabad"
  },
  {
    "district_name": "Kolat"
  },
  {
    "district_name": "Krishnanagar Ahmedabad"
  },
  {
    "district_name": "Kubadthal"
  },
  {
    "district_name": "Kubernagar B A"
  },
  {
    "district_name": "Kubernagar"
  },
  {
    "district_name": "Kuha"
  },
  {
    "district_name": "Kujad"
  },
  {
    "district_name": "L G Hospital"
  },
  {
    "district_name": "Lal Darwaja"
  },
  {
    "district_name": "Lambha"
  },
  {
    "district_name": "Limbadia"
  },
  {
    "district_name": "M D Marg"
  },
  {
    "district_name": "Madhupura Market"
  },
  {
    "district_name": "Mahijada"
  },
  {
    "district_name": "Manek Chowk"
  },
  {
    "district_name": "Manekbag"
  },
  {
    "district_name": "Maninagar"
  },
  {
    "district_name": "Medra"
  },
  {
    "district_name": "Meghaningar"
  },
  {
    "district_name": "Memnagar"
  },
  {
    "district_name": "Miroli"
  },
  {
    "district_name": "Motera"
  },
  {
    "district_name": "Muktipur"
  },
  {
    "district_name": "Municipal Corporation"
  },
  {
    "district_name": "N C Market"
  },
  {
    "district_name": "N C Mills"
  },
  {
    "district_name": "Nana Chiloda"
  },
  {
    "district_name": "Nandej"
  },
  {
    "district_name": "Naranpura Vistar"
  },
  {
    "district_name": "Narayannagar"
  },
  {
    "district_name": "Naroda I E"
  },
  {
    "district_name": "Naroda Road"
  },
  {
    "district_name": "Naroda S A"
  },
  {
    "district_name": "Naroda"
  },
  {
    "district_name": "Narol"
  },
  {
    "district_name": "Nava Vadaj"
  },
  {
    "district_name": "Navapura"
  },
  {
    "district_name": "Navjivan"
  },
  {
    "district_name": "Navrangpura"
  },
  {
    "district_name": "Nikol"
  },
  {
    "district_name": "Noblenagar"
  },
  {
    "district_name": "O N G C"
  },
  {
    "district_name": "Ode"
  },
  {
    "district_name": "Odhav Industrial Estate"
  },
  {
    "district_name": "Odhav"
  },
  {
    "district_name": "Paldi Kankaj"
  },
  {
    "district_name": "Paldi Ahmedabad"
  },
  {
    "district_name": "Pardhol"
  },
  {
    "district_name": "Pasunj"
  },
  {
    "district_name": "Pirana"
  },
  {
    "district_name": "Polytechnic Ahmedabad"
  },
  {
    "district_name": "Public Office Ahmedabad"
  },
  {
    "district_name": "Raikhad"
  },
  {
    "district_name": "Railway Colony Ahmedabad"
  },
  {
    "district_name": "Railwaypura"
  },
  {
    "district_name": "Raipur Ahmedabad"
  },
  {
    "district_name": "Rajpur Gomtipur"
  },
  {
    "district_name": "Rakhial"
  },
  {
    "district_name": "Rakhial Udyog Vistar"
  },
  {
    "district_name": "Ranip"
  },
  {
    "district_name": "Ranodra"
  },
  {
    "district_name": "Revdibazar"
  },
  {
    "district_name": "S A C"
  },
  {
    "district_name": "Sabarmati"
  },
  {
    "district_name": "Saijpur"
  },
  {
    "district_name": "Saijpur Bogha"
  },
  {
    "district_name": "Sanathal"
  },
  {
    "district_name": "Saraspur"
  },
  {
    "district_name": "Sardarnagar"
  },
  {
    "district_name": "Sarkhej Road"
  },
  {
    "district_name": "Sarkhej"
  },
  {
    "district_name": "Shah Alam Roza"
  },
  {
    "district_name": "Shahibag"
  },
  {
    "district_name": "Shahpur Ahmedabad"
  },
  {
    "district_name": "Shahwadi"
  },
  {
    "district_name": "Shardanagar"
  },
  {
    "district_name": "Shastrinagar Ahmedabad"
  },
  {
    "district_name": "Shela"
  },
  {
    "district_name": "Sola H B C"
  },
  {
    "district_name": "Stadium Marg"
  },
  {
    "district_name": "Sub Foreign"
  },
  {
    "district_name": "Sukhrampura"
  },
  {
    "district_name": "T B Nagar"
  },
  {
    "district_name": "Telav"
  },
  {
    "district_name": "Thaltej Road"
  },
  {
    "district_name": "Timba"
  },
  {
    "district_name": "Undrel"
  },
  {
    "district_name": "Vadaj"
  },
  {
    "district_name": "Vadod"
  },
  {
    "district_name": "Vasai"
  },
  {
    "district_name": "Vasisthnagar"
  },
  {
    "district_name": "Vastral"
  },
  {
    "district_name": "Vatva"
  },
  {
    "district_name": "Vehlal"
  },
  {
    "district_name": "Vishalpur"
  },
  {
    "district_name": "Zanu"
  },
  {
    "district_name": "Ahmedabad G.P.O."
  },
  {
    "district_name": "Abasana"
  },
  {
    "district_name": "Adroda"
  },
  {
    "district_name": "Adval"
  },
  {
    "district_name": "Akru"
  },
  {
    "district_name": "Alampur"
  },
  {
    "district_name": "Alau"
  },
  {
    "district_name": "Ambaliara"
  },
  {
    "district_name": "Ambareli"
  },
  {
    "district_name": "Andej"
  },
  {
    "district_name": "Aniali K"
  },
  {
    "district_name": "Aniali Bhimji"
  },
  {
    "district_name": "Arnej"
  },
  {
    "district_name": "Asalgam"
  },
  {
    "district_name": "Ashoknagar"
  },
  {
    "district_name": "Badarkha"
  },
  {
    "district_name": "Bagad"
  },
  {
    "district_name": "Bagodara"
  },
  {
    "district_name": "Bajarda"
  },
  {
    "district_name": "Bakrana"
  },
  {
    "district_name": "Baldana"
  },
  {
    "district_name": "Balsasan"
  },
  {
    "district_name": "Bamroli"
  },
  {
    "district_name": "Bamsara"
  },
  {
    "district_name": "Barwala Ghelasha"
  },
  {
    "district_name": "Bavaliary"
  },
  {
    "district_name": "Bavla Market Yard"
  },
  {
    "district_name": "Bavla"
  },
  {
    "district_name": "Bhadaj"
  },
  {
    "district_name": "Bhadana"
  },
  {
    "district_name": "Bhadiad"
  },
  {
    "district_name": "Bhangadh"
  },
  {
    "district_name": "Bhankoda"
  },
  {
    "district_name": "Bhayla"
  },
  {
    "district_name": "Bhojwa"
  },
  {
    "district_name": "Bholad"
  },
  {
    "district_name": "Bhoyani"
  },
  {
    "district_name": "Bhurkhi"
  },
  {
    "district_name": "Bodia"
  },
  {
    "district_name": "Bol"
  },
  {
    "district_name": "Bordibazar Viramgam"
  },
  {
    "district_name": "Buranpur"
  },
  {
    "district_name": "Chaloda"
  },
  {
    "district_name": "Chandarva"
  },
  {
    "district_name": "Chandisar"
  },
  {
    "district_name": "Chandlodia"
  },
  {
    "district_name": "Chandranagar"
  },
  {
    "district_name": "Changodar"
  },
  {
    "district_name": "Charanki"
  },
  {
    "district_name": "Charel"
  },
  {
    "district_name": "Chekhla"
  },
  {
    "district_name": "Chhabasar"
  },
  {
    "district_name": "Chhaniar"
  },
  {
    "district_name": "Chharodi"
  },
  {
    "district_name": "Chhasiana"
  },
  {
    "district_name": "Chiada"
  },
  {
    "district_name": "Chokdi"
  },
  {
    "district_name": "Chuval Dangarva"
  },
  {
    "district_name": "Dabhsar"
  },
  {
    "district_name": "Dadhana"
  },
  {
    "district_name": "Daduka"
  },
  {
    "district_name": "Dadusar"
  },
  {
    "district_name": "Dalod"
  },
  {
    "district_name": "Daran"
  },
  {
    "district_name": "Daslana"
  },
  {
    "district_name": "Dehgamda"
  },
  {
    "district_name": "Dekawada"
  },
  {
    "district_name": "Deo Dholera"
  },
  {
    "district_name": "Detroj"
  },
  {
    "district_name": "Devaliya"
  },
  {
    "district_name": "Devpura"
  },
  {
    "district_name": "Devtimoti"
  },
  {
    "district_name": "Dhakdi"
  },
  {
    "district_name": "Dhanala"
  },
  {
    "district_name": "Dhandhuka"
  },
  {
    "district_name": "Dhanwada"
  },
  {
    "district_name": "Dharpipla"
  },
  {
    "district_name": "Dhedasana"
  },
  {
    "district_name": "Dhingada"
  },
  {
    "district_name": "Dholera"
  },
  {
    "district_name": "Dholi"
  },
  {
    "district_name": "Dholka"
  },
  {
    "district_name": "Digvijaynagar"
  },
  {
    "district_name": "Dodar"
  },
  {
    "district_name": "Dumana"
  },
  {
    "district_name": "Durgi"
  },
  {
    "district_name": "Endla"
  },
  {
    "district_name": "Fangadi"
  },
  {
    "district_name": "Fatepur"
  },
  {
    "district_name": "Fedra"
  },
  {
    "district_name": "Galsana"
  },
  {
    "district_name": "Gamanpura"
  },
  {
    "district_name": "Gamph"
  },
  {
    "district_name": "Gangad"
  },
  {
    "district_name": "Ganol"
  },
  {
    "district_name": "Garodia"
  },
  {
    "district_name": "Gatrad"
  },
  {
    "district_name": "Ghatisana"
  },
  {
    "district_name": "Ghoda"
  },
  {
    "district_name": "Godhavata"
  },
  {
    "district_name": "Godhavi"
  },
  {
    "district_name": "Gogla"
  },
  {
    "district_name": "Goraiya"
  },
  {
    "district_name": "Goraj"
  },
  {
    "district_name": "Gorasu"
  },
  {
    "district_name": "Gota"
  },
  {
    "district_name": "Gunda"
  },
  {
    "district_name": "Gundi Sarvodaya Ashram"
  },
  {
    "district_name": "Gunjala"
  },
  {
    "district_name": "Gunjar"
  },
  {
    "district_name": "Hansalpur"
  },
  {
    "district_name": "Hathijan"
  },
  {
    "district_name": "Hebatpur"
  },
  {
    "district_name": "Hirapura"
  },
  {
    "district_name": "Iawa Vasna"
  },
  {
    "district_name": "Ingoli"
  },
  {
    "district_name": "Jagatpur"
  },
  {
    "district_name": "Jakhada"
  },
  {
    "district_name": "Jakwada"
  },
  {
    "district_name": "Jalalpur Vajifa"
  },
  {
    "district_name": "Jalampur"
  },
  {
    "district_name": "Jalila"
  },
  {
    "district_name": "Jalisana"
  },
  {
    "district_name": "Jaliya"
  },
  {
    "district_name": "Jamp"
  },
  {
    "district_name": "Jantanagar"
  },
  {
    "district_name": "Jawaraj"
  },
  {
    "district_name": "Jeska"
  },
  {
    "district_name": "Jholapur"
  },
  {
    "district_name": "Joshipura"
  },
  {
    "district_name": "Junapadhar"
  },
  {
    "district_name": "Juval"
  },
  {
    "district_name": "Juval Rupavati"
  },
  {
    "district_name": "Kadipur"
  },
  {
    "district_name": "Kadvasan"
  },
  {
    "district_name": "Kalana"
  },
  {
    "district_name": "Kali"
  },
  {
    "district_name": "Kalyangadh"
  },
  {
    "district_name": "Kamiala"
  },
  {
    "district_name": "Kamijala"
  },
  {
    "district_name": "Kaneti"
  },
  {
    "district_name": "Kankravadi"
  },
  {
    "district_name": "Kanz"
  },
  {
    "district_name": "Karakthal"
  },
  {
    "district_name": "Katosan Road"
  },
  {
    "district_name": "Kauka"
  },
  {
    "district_name": "Kavitha"
  },
  {
    "district_name": "Kelia Vasna"
  },
  {
    "district_name": "Kerala"
  },
  {
    "district_name": "Keria"
  },
  {
    "district_name": "Kesardi"
  },
  {
    "district_name": "Khadol"
  },
  {
    "district_name": "Khambhada"
  },
  {
    "district_name": "Khamidana"
  },
  {
    "district_name": "Khandachora Dhandhuka"
  },
  {
    "district_name": "Kharad"
  },
  {
    "district_name": "Kharakuva Dholka"
  },
  {
    "district_name": "Khas"
  },
  {
    "district_name": "Khasta"
  },
  {
    "district_name": "Khoda"
  },
  {
    "district_name": "Khodiyar"
  },
  {
    "district_name": "Khokarnesh"
  },
  {
    "district_name": "Khorajnanoda"
  },
  {
    "district_name": "Khudad"
  },
  {
    "district_name": "Khun"
  },
  {
    "district_name": "Kocharia"
  },
  {
    "district_name": "Kointia"
  },
  {
    "district_name": "Kokta"
  },
  {
    "district_name": "Koth"
  },
  {
    "district_name": "Kothadia"
  },
  {
    "district_name": "Kukvav"
  },
  {
    "district_name": "Kumarkhan"
  },
  {
    "district_name": "Kundal"
  },
  {
    "district_name": "Kundli"
  },
  {
    "district_name": "Kunpur"
  },
  {
    "district_name": "Kunvar"
  },
  {
    "district_name": "Lapkaman"
  },
  {
    "district_name": "Loliya"
  },
  {
    "district_name": "Lothal Bhurkhi RS"
  },
  {
    "district_name": "Madrisana"
  },
  {
    "district_name": "Makhiav"
  },
  {
    "district_name": "Mandal Ahmedabad"
  },
  {
    "district_name": "Manipur"
  },
  {
    "district_name": "Mankol"
  },
  {
    "district_name": "Marusana"
  },
  {
    "district_name": "Matoda"
  },
  {
    "district_name": "Melaj"
  },
  {
    "district_name": "Mingalpur"
  },
  {
    "district_name": "Mithapur"
  },
  {
    "district_name": "Modasar"
  },
  {
    "district_name": "Moraiya"
  },
  {
    "district_name": "Mota Tradia"
  },
  {
    "district_name": "Moti Kishol"
  },
  {
    "district_name": "Moti Boru"
  },
  {
    "district_name": "Moti Rantai"
  },
  {
    "district_name": "Moti Vavdi"
  },
  {
    "district_name": "Nadishala"
  },
  {
    "district_name": "Nana Ubhada"
  },
  {
    "district_name": "Nani Boru"
  },
  {
    "district_name": "Nani Devti"
  },
  {
    "district_name": "Nani Vavdi"
  },
  {
    "district_name": "Nanodara"
  },
  {
    "district_name": "Navagam"
  },
  {
    "district_name": "Navda"
  },
  {
    "district_name": "Nayakpur"
  },
  {
    "district_name": "Nedharad"
  },
  {
    "district_name": "Nesda"
  },
  {
    "district_name": "Ogan"
  },
  {
    "district_name": "Ognaj"
  },
  {
    "district_name": "Otaria"
  },
  {
    "district_name": "Otaria Sarvodaya Ashram"
  },
  {
    "district_name": "Padana"
  },
  {
    "district_name": "Panar"
  },
  {
    "district_name": "Panchham"
  },
  {
    "district_name": "Panchhi"
  },
  {
    "district_name": "Pandharpura"
  },
  {
    "district_name": "Parabadi"
  },
  {
    "district_name": "Pimpan"
  },
  {
    "district_name": "Piplaj"
  },
  {
    "district_name": "Pipli"
  },
  {
    "district_name": "Pisawada"
  },
  {
    "district_name": "Polarpur"
  },
  {
    "district_name": "Rahemalpur"
  },
  {
    "district_name": "Rajoda"
  },
  {
    "district_name": "Rajpura"
  },
  {
    "district_name": "Rakhiana"
  },
  {
    "district_name": "Ramol"
  },
  {
    "district_name": "Rampur"
  },
  {
    "district_name": "Rampura"
  },
  {
    "district_name": "Rampura Ahmedabad"
  },
  {
    "district_name": "Ranesar"
  },
  {
    "district_name": "Rangpur"
  },
  {
    "district_name": "Ranoda"
  },
  {
    "district_name": "Ranpur"
  },
  {
    "district_name": "Rasam"
  },
  {
    "district_name": "Rayka"
  },
  {
    "district_name": "Refda"
  },
  {
    "district_name": "Rethal"
  },
  {
    "district_name": "Ribadi"
  },
  {
    "district_name": "Rohika"
  },
  {
    "district_name": "Rojid"
  },
  {
    "district_name": "Rojka"
  },
  {
    "district_name": "Rudatal"
  },
  {
    "district_name": "Rupal"
  },
  {
    "district_name": "Rupgadh"
  },
  {
    "district_name": "Sachana"
  },
  {
    "district_name": "Sadatpura"
  },
  {
    "district_name": "Sahij"
  },
  {
    "district_name": "Saiwada"
  },
  {
    "district_name": "Salajada"
  },
  {
    "district_name": "Salangpur Hanuman"
  },
  {
    "district_name": "Salasar"
  },
  {
    "district_name": "Sanand"
  },
  {
    "district_name": "Sandhida"
  },
  {
    "district_name": "Sangasar"
  },
  {
    "district_name": "Sangpura"
  },
  {
    "district_name": "Sankod"
  },
  {
    "district_name": "Sarandi"
  },
  {
    "district_name": "Sargwala"
  },
  {
    "district_name": "Sari"
  },
  {
    "district_name": "Saroda"
  },
  {
    "district_name": "Sarsavadi"
  },
  {
    "district_name": "Sathal"
  },
  {
    "district_name": "Shahpur"
  },
  {
    "district_name": "Sher"
  },
  {
    "district_name": "Sherpura"
  },
  {
    "district_name": "Shilaj"
  },
  {
    "district_name": "Shivpura"
  },
  {
    "district_name": "Shiyal"
  },
  {
    "district_name": "Siawada"
  },
  {
    "district_name": "Sihor"
  },
  {
    "district_name": "Simej"
  },
  {
    "district_name": "Sinaj"
  },
  {
    "district_name": "Sindharej"
  },
  {
    "district_name": "Sitapur"
  },
  {
    "district_name": "Sobhasan"
  },
  {
    "district_name": "Sodhi"
  },
  {
    "district_name": "Sola"
  },
  {
    "district_name": "Solgam"
  },
  {
    "district_name": "Sunderiana"
  },
  {
    "district_name": "Sunvala"
  },
  {
    "district_name": "Tagadi"
  },
  {
    "district_name": "Telavi"
  },
  {
    "district_name": "Thaltej"
  },
  {
    "district_name": "Thori Mubarak"
  },
  {
    "district_name": "Thori Thumbha"
  },
  {
    "district_name": "Thuleta"
  },
  {
    "district_name": "Tragad"
  },
  {
    "district_name": "Transad"
  },
  {
    "district_name": "Trent"
  },
  {
    "district_name": "Ughroj"
  },
  {
    "district_name": "Ukardi"
  },
  {
    "district_name": "Ukhlod"
  },
  {
    "district_name": "Umrela"
  },
  {
    "district_name": "Unchadi"
  },
  {
    "district_name": "Upardal"
  },
  {
    "district_name": "Utelia"
  },
  {
    "district_name": "Vadgas"
  },
  {
    "district_name": "Vadhela"
  },
  {
    "district_name": "Vagad"
  },
  {
    "district_name": "Valdhera"
  },
  {
    "district_name": "Valhia"
  },
  {
    "district_name": "Valinda"
  },
  {
    "district_name": "Vanch"
  },
  {
    "district_name": "Vani"
  },
  {
    "district_name": "Vanpardi"
  },
  {
    "district_name": "Vansva"
  },
  {
    "district_name": "Vanthal"
  },
  {
    "district_name": "Varmor"
  },
  {
    "district_name": "Varna"
  },
  {
    "district_name": "Vasna Iawa"
  },
  {
    "district_name": "Vasna Chacharvadi"
  },
  {
    "district_name": "Vasna"
  },
  {
    "district_name": "Vataman"
  },
  {
    "district_name": "Vatva Industrial Estate"
  },
  {
    "district_name": "Vautha"
  },
  {
    "district_name": "Vejalka"
  },
  {
    "district_name": "Vekaria"
  },
  {
    "district_name": "Vinchhan"
  },
  {
    "district_name": "Vinchhiya"
  },
  {
    "district_name": "Vinzol"
  },
  {
    "district_name": "Vinzuvada"
  },
  {
    "district_name": "Viramgam"
  },
  {
    "district_name": "Virdi"
  },
  {
    "district_name": "Virochannagar"
  },
  {
    "district_name": "Vithlpura"
  },
  {
    "district_name": "VivekanandNagar"
  },
  {
    "district_name": "Zanzarka"
  },
  {
    "district_name": "Zanzarva"
  },
  {
    "district_name": "Zezra"
  },
  {
    "district_name": "Zinzar"
  },
  {
    "district_name": "Ambalia"
  }
]